bv/__init__.py
bv/runtime/__init__.py
bv/runtime/_guard.py
bv/runtime/assets.py
bv/runtime/auth.py
bv/runtime/client.py
bv/runtime/context.py
bv/runtime/credential.py
bv/runtime/logging.py
bv/runtime/queue.py
bv/runtime/queue_item.py
bv/runtime/queues.py
bv/runtime/secret.py
bv/runtime/traces.py
bv/runtime/url_resolver.py
bv_runtime-0.2.6.dist-info/METADATA
bv_runtime-0.2.6.dist-info/WHEEL
bv_runtime-0.2.6.dist-info/RECORD
