Metadata-Version: 2.4
Name: bv-runtime
Version: 0.2.6
Summary: Runtime SDK for Bot Velocity automations
Author: Bot Velocity Team
License: Proprietary
Keywords: agentic,bot-velocity,rpa,runtime
Requires-Python: >=3.10
Requires-Dist: httpx>=0.24.0
Requires-Dist: tenacity>=8.0.0
